{
    "overworld-cinnabar": {
        "template": "uniform",
        "block": {
            "name": "Thaumcraft:blockCustomOre",
            "metadata": 0
        },
        "material": "stone",
        "clusterSize": 6,
        "numClusters": 4,
        "maxHeight": 64,
        "minHeight": 48,
        "retrogen": "false",
        "biomeRestriction": "whitelist",
        "biomes": [
            {"type": "name", "entry": "Oasis"},
            {"type": "dictionary", "entry": "MAGICAL"}
        ],
        "dimensionRestriction": "whitelist",
        "dimensions": [
            0
        ]
    },
    "overworld-amber": {
        "template": "uniform",
        "block": {
            "name": "Thaumcraft:blockCustomOre",
            "metadata": 7
        },
        "material": "stone",
        "clusterSize": 4,
        "numClusters": 4,
        "maxHeight": 48,
        "minHeight": 32,
        "retrogen": "false",
        "biomeRestriction": "whitelist",
        "biomes": [
            {"type": "name", "entry": "Oasis"},
            {"type": "dictionary", "entry": "MAGICAL"}
        ],
        "dimensionRestriction": "whitelist",
        "dimensions": [
            0
        ]
    },
    "overworld-infused-air": {
        "template": "uniform",
        "block": {
            "name": "Thaumcraft:blockCustomOre",
            "metadata": 1
        },
        "material": "stone",
        "clusterSize": 4,
        "numClusters": 8,
        "maxHeight": 64,
        "minHeight": 50,
        "retrogen": "false",
        "biomeRestriction": "whitelist",
        "biomes": [
            {"type": "name", "entry": "Oasis"},
            {"type": "dictionary", "entry": "MAGICAL"}
        ],
        "dimensionRestriction": "whitelist",
        "dimensions": [
            0
        ]
    },
    "overworld-infused-fire": {
        "template": "uniform",
        "block": {
            "name": "Thaumcraft:blockCustomOre",
            "metadata": 2
        },
        "material": "stone",
        "clusterSize": 6,
        "numClusters": 8,
        "maxHeight": 60,
        "minHeight": 50,
        "retrogen": "false",
        "biomeRestriction": "whitelist",
        "biomes": [
            {"type": "name", "entry": "Oasis"},
            {"type": "dictionary", "entry": "MAGICAL"}
        ],
        "dimensionRestriction": "whitelist",
        "dimensions": [
            0
        ]
    },
    "overworld-infused-water": {
        "template": "uniform",
        "block": {
            "name": "Thaumcraft:blockCustomOre",
            "metadata": 3
        },
        "material": "stone",
        "clusterSize": 4,
        "numClusters": 8,
        "maxHeight": 50,
        "minHeight": 40,
        "retrogen": "false",
        "biomeRestriction": "whitelist",
        "biomes": [
            {"type": "name", "entry": "Oasis"},
            {"type": "dictionary", "entry": "MAGICAL"}
        ],
        "dimensionRestriction": "whitelist",
        "dimensions": [
            0
        ]
    },
    "overworld-infused-earth": {
        "template": "uniform",
        "block": {
            "name": "Thaumcraft:blockCustomOre",
            "metadata": 4
        },
        "material": "stone",
        "clusterSize": 4,
        "numClusters": 8,
        "maxHeight": 40,
        "minHeight": 30,
        "retrogen": "false",
        "biomeRestriction": "whitelist",
        "biomes": [
            {"type": "name", "entry": "Oasis"},
            {"type": "dictionary", "entry": "MAGICAL"}
        ],
        "dimensionRestriction": "whitelist",
        "dimensions": [
            0
        ]
    },
    "overworld-infused-order": {
        "template": "uniform",
        "block": {
            "name": "Thaumcraft:blockCustomOre",
            "metadata": 5
        },
        "material": "stone",
        "clusterSize": 4,
        "numClusters": 8,
        "maxHeight": 30,
        "minHeight": 20,
        "retrogen": "false",
        "biomeRestriction": "whitelist",
        "biomes": [
            {"type": "name", "entry": "Oasis"},
            {"type": "dictionary", "entry": "MAGICAL"}
        ],
        "dimensionRestriction": "whitelist",
        "dimensions": [
            0
        ]
    },
    "overworld-infused-entropy": {
        "template": "uniform",
        "block": {
            "name": "Thaumcraft:blockCustomOre",
            "metadata": 6
        },
        "material": "stone",
        "clusterSize": 4,
        "numClusters": 8,
        "maxHeight": 20,
        "minHeight": 10,
        "retrogen": "false",
        "biomeRestriction": "whitelist",
        "biomes": [
            {"type": "name", "entry": "Oasis"},
            {"type": "dictionary", "entry": "MAGICAL"}
        ],
        "dimensionRestriction": "whitelist",
        "dimensions": [
            0
        ]
    }
}